clickup_python_sdk/__init__.py
clickup_python_sdk/api.py
clickup_python_sdk/config.py
clickup_python_sdk/exceptions.py
clickup_python_sdk/clickupobjects/__init__.py
clickup_python_sdk/clickupobjects/abstractobject.py
clickup_python_sdk/clickupobjects/checklist.py
clickup_python_sdk/clickupobjects/checklistitem.py
clickup_python_sdk/clickupobjects/comment.py
clickup_python_sdk/clickupobjects/customfield.py
clickup_python_sdk/clickupobjects/dependency.py
clickup_python_sdk/clickupobjects/document.py
clickup_python_sdk/clickupobjects/documentpage.py
clickup_python_sdk/clickupobjects/folder.py
clickup_python_sdk/clickupobjects/group.py
clickup_python_sdk/clickupobjects/list.py
clickup_python_sdk/clickupobjects/space.py
clickup_python_sdk/clickupobjects/tags.py
clickup_python_sdk/clickupobjects/task.py
clickup_python_sdk/clickupobjects/tasktemplate.py
clickup_python_sdk/clickupobjects/team.py
clickup_python_sdk/clickupobjects/timeentry.py
clickup_python_sdk/clickupobjects/user.py
clickup_python_sdk/clickupobjects/view.py
clickup_python_sdk-2.0.1.dist-info/licenses/LICENSE.txt
tests/__init__.py
clickup_python_sdk-2.0.1.dist-info/METADATA
clickup_python_sdk-2.0.1.dist-info/WHEEL
clickup_python_sdk-2.0.1.dist-info/top_level.txt
clickup_python_sdk-2.0.1.dist-info/RECORD
