Metadata-Version: 2.4
Name: clickup-python-sdk
Version: 2.0.1
Summary: Python SDK for the ClickUp API
Home-page: https://github.com/MB0390231/clickup_python_sdk
Author: Michael Broyles
Author-email: michaelbroyles68@gmail.com
Project-URL: Bug Tracker, https://github.com/MB0390231/clickup_python_sdk/issues
Project-URL: Documentation, https://github.com/MB0390231/clickup_python_sdk
Project-URL: Source Code, https://github.com/MB0390231/clickup_python_sdk
Keywords: clickup,api,sdk,productivity,task management
Classifier: Development Status :: 4 - Beta
Classifier: Intended Audience :: Developers
Classifier: License :: OSI Approved :: GNU General Public License v3 (GPLv3)
Classifier: Programming Language :: Python :: 3
Classifier: Programming Language :: Python :: 3.7
Classifier: Programming Language :: Python :: 3.8
Classifier: Programming Language :: Python :: 3.9
Classifier: Programming Language :: Python :: 3.10
Classifier: Programming Language :: Python :: 3.11
Classifier: Programming Language :: Python :: 3.12
Classifier: Topic :: Software Development :: Libraries
Classifier: Topic :: Software Development :: Libraries :: Python Modules
Requires-Python: >=3.7
License-File: LICENSE.txt
Requires-Dist: requests>=2.32.3
Requires-Dist: certifi>=2025.1.31
Requires-Dist: charset-normalizer>=3.4.1
Requires-Dist: idna>=3.10
Requires-Dist: urllib3>=2.4.0
Dynamic: author
Dynamic: author-email
Dynamic: classifier
Dynamic: description
Dynamic: description-content-type
Dynamic: home-page
Dynamic: keywords
Dynamic: license-file
Dynamic: project-url
Dynamic: requires-dist
Dynamic: requires-python
Dynamic: summary
